physanim/__init__.py
physanim/core.py
physanim/interaction.py
physanim/systems.py
physanim-0.1.2.dist-info/METADATA
physanim-0.1.2.dist-info/WHEEL
physanim-0.1.2.dist-info/top_level.txt
physanim-0.1.2.dist-info/RECORD
