Metadata-Version: 2.4
Name: physanim
Version: 0.1.2
Summary: A lightweight physics animation library
Author-email: Ayush Kumar Jha <jhaayushkumar@gmail.com>
Project-URL: Homepage, https://github.com/yourusername/physanim
Classifier: Programming Language :: Python :: 3
Classifier: License :: OSI Approved :: MIT License
Classifier: Operating System :: OS Independent
Requires-Python: >=3.7
Requires-Dist: numpy
Requires-Dist: matplotlib
Requires-Dist: scipy
Provides-Extra: interactive
Requires-Dist: ipywidgets; extra == "interactive"
Requires-Dist: ipympl; extra == "interactive"
